Spreadsheet1234/__init__.py
nidhichaudharygsmtpd007-1.0.6.dist-info/METADATA
nidhichaudharygsmtpd007-1.0.6.dist-info/WHEEL
nidhichaudharygsmtpd007-1.0.6.dist-info/top_level.txt
nidhichaudharygsmtpd007-1.0.6.dist-info/RECORD
